vision_agent/__init__.py
vision_agent/.sim_tools/df.csv
vision_agent/.sim_tools/embs.npy
vision_agent/agent/README.md
vision_agent/agent/__init__.py
vision_agent/agent/agent.py
vision_agent/agent/vision_agent_coder_prompts_v2.py
vision_agent/agent/vision_agent_coder_v2.py
vision_agent/agent/vision_agent_planner_prompts_v2.py
vision_agent/agent/vision_agent_planner_v2.py
vision_agent/agent/vision_agent_prompts_v2.py
vision_agent/agent/vision_agent_prompts_v3.py
vision_agent/agent/vision_agent_v2.py
vision_agent/agent/vision_agent_v3.py
vision_agent/agent/visual_design_patterns.py
vision_agent/clients/__init__.py
vision_agent/clients/http.py
vision_agent/configs/__init__.py
vision_agent/configs/anthropic_config.py
vision_agent/configs/config.py
vision_agent/configs/openai_config.py
vision_agent/fonts/__init__.py
vision_agent/fonts/default_font_ch_en.ttf
vision_agent/lmm/__init__.py
vision_agent/lmm/lmm.py
vision_agent/models/__init__.py
vision_agent/models/agent_types.py
vision_agent/models/lmm_types.py
vision_agent/models/tools_types.py
vision_agent/sim/__init__.py
vision_agent/sim/sim.py
vision_agent/tools/__init__.py
vision_agent/tools/meta_tools.py
vision_agent/tools/planner_tools.py
vision_agent/tools/planner_v3_tools.py
vision_agent/tools/prompts.py
vision_agent/tools/suggestion.py
vision_agent/tools/tools.py
vision_agent/utils/__init__.py
vision_agent/utils/agent.py
vision_agent/utils/exceptions.py
vision_agent/utils/execute.py
vision_agent/utils/image_utils.py
vision_agent/utils/tools.py
vision_agent/utils/tools_doc.py
vision_agent/utils/video.py
vision_agent/utils/video_tracking.py
vision_agent-1.1.20.dist-info/METADATA
vision_agent-1.1.20.dist-info/WHEEL
vision_agent-1.1.20.dist-info/licenses/LICENSE
vision_agent-1.1.20.dist-info/RECORD
