Metadata-Version: 2.4
Name: vision-agent
Version: 1.1.20
Summary: Toolset for Vision Agent
Project-URL: Homepage, https://landing.ai
Project-URL: repository, https://github.com/landing-ai/vision-agent
Project-URL: documentation, https://github.com/landing-ai/vision-agent
Author-email: Landing AI <dev@landing.ai>
License-File: LICENSE
Requires-Python: <4.0,>=3.9
Requires-Dist: anthropic>=0.54.0
Requires-Dist: av<12,>=11.0.0
Requires-Dist: dotenv<0.10,>=0.9.9
Requires-Dist: flake8<8,>=7.0.0
Requires-Dist: google-genai<2,>=1.0.0
Requires-Dist: httpx==0.27.2
Requires-Dist: ipykernel<7,>=6.29.4
Requires-Dist: libcst<2,>=1.5.0
Requires-Dist: matplotlib<4,>=3.9.2
Requires-Dist: nbclient<0.11,>=0.10.0
Requires-Dist: nbformat<6,>=5.10.4
Requires-Dist: numpy<2.0.0,>=1.21.0
Requires-Dist: openai>=1.86.0
Requires-Dist: opencv-python==4.*
Requires-Dist: opentelemetry-api<2,>=1.29.0
Requires-Dist: pandas==2.*
Requires-Dist: pillow-heif<0.17,>=0.16.0
Requires-Dist: pillow==10.*
Requires-Dist: pydantic<3,>=2.0.0
Requires-Dist: pymupdf<2,>=1.23.0
Requires-Dist: requests==2.*
Requires-Dist: rich<14,>=13.7.1
Requires-Dist: scikit-learn<2,>=1.5.2
Requires-Dist: scipy==1.13.*
Requires-Dist: tabulate<0.10,>=0.9.0
Requires-Dist: tenacity<9,>=8.3.0
Requires-Dist: tqdm<5.0.0,>=4.64.0
Requires-Dist: typing-extensions==4.*
Requires-Dist: yt-dlp>=2025.6.9
